koui/__init__.py
koui/_modidx.py
koui/api.py
koui-1.3.dist-info/LICENSE
koui-1.3.dist-info/METADATA
koui-1.3.dist-info/WHEEL
koui-1.3.dist-info/top_level.txt
koui-1.3.dist-info/RECORD
