Metadata-Version: 2.1
Name: koui
Version: 1.3
Summary: テキスト間の校異情報を扱うライプラリです。
Home-page: https://github.com/ldasjp8/koui
Author: nakamura196
Author-email: na.kamura.1263@gmail.com
Classifier: Programming Language :: Python :: 3
Classifier: License :: OSI Approved :: MIT License
Classifier: Operating System :: OS Independent
License-File: LICENSE
Requires-Dist: beautifulsoup4
Requires-Dist: levenshtein
